{
    "id": 3,
    "description": "Exploring the humorous dynamics between a gossipy water drop and a methodical printer.",
    "title": "Office Secrets",
    "c1_name": "Leaky",
    "c2_name": "Printy",
    "c1_gender": "female",
    "c2_gender": "other",
    "n_1": "Leaky shares the latest gossip with Printy at the water cooler.",
    "n_2": "Leaky, the center of attention, whispers to a group of office supplies.",
    "n_3": "Printy, overwhelmed by the overload of information, struggles to keep up.",
    "n_4": "In a chaotic finale, Printy jams, and Leaky overflows with laughter.",
    "c1_1": "You won't believe what I heard today!",
    "c2_1": "Please, I'm just a printer...",
    "c1_2": "And then, guess what happened next?",
    "c2_2": "Is this really happening?",
    "c1_3": "Haha, you look jammed, Printy!",
    "c2_3": "I am not designed for this!",
    "c1_4": "This is why we can't have secrets here!",
    "c2_4": "I'm literally jammed because of your leaks!",
    "script_flow": [
        "n_1",
        "c1_1",
        "c2_1",
        "n_2",
        "c1_2",
        "c2_2",
        "n_3",
        "c1_3",
        "c2_3",
        "n_4",
        "c1_4",
        "c2_4"
    ],
    "image_id": "z3o2sV5oJOzDDwa1"
}