{
    "description": "A charming story set in Britain, where a chocolate expresses its affection with a tea-themed compliment on Valentine's Day.",
    "title": "Tea-riffic Love",
    "c1_name": "Choco",
    "c2_name": "Tea-Cup",
    "c1_gender": "male",
    "c2_gender": "female",
    "n_1": "In a quaint British teashop, Choco was preparing a special surprise for Tea-Cup.",
    "c1_1": "Tea-Cup, I have something sweet to say...",
    "c2_1": "Oh, what is it, Choco?",
    "n_2": "Choco, with a bashful smile, shared his heartfelt feelings.",
    "c1_2": "You're tea-riffically sweet, my dear!",
    "c2_2": "Choco, that's so charming!",
    "n_3": "Tea-Cup blushed, her steam swirling in delight.",
    "c1_3": "Will you be my Valentine, Tea-Cup?",
    "c2_3": "Yes, Choco! You make my heart brew!",
    "n_4": "And so, amidst the cozy teashop setting, Choco and Tea-Cup celebrated their love, tea-riffically sweet.",
    "c1_4": "Happy Valentine's, my tea-lightful love!",
    "c2_4": "Happy Valentine's, my sweet Choco!",
    "script_flow": [
        "n_1",
        "c1_1",
        "c2_1",
        "n_2",
        "c1_2",
        "c2_2",
        "n_3",
        "c1_3",
        "c2_3",
        "n_4",
        "c1_4",
        "c2_4"
    ],
    "id": 85,
    "image_id": "O8mWBCmbRUrPqLxD"
}